<entity tablename="out" defaultOrderField="student_id" logicDelete="false">
	<field name="student_id"
			defaultValue="0"
			type="integer"
			primaryKey="true"
			required="true"
			autoinc="false"
			logicDeleteMark="false">
			<fk_info entity="student.xml"
						referencedField="id"
						substituteField="id">
			</fk_info>	</field>
	<field name="cause__id"
			defaultValue="0"
			type="integer"
			primaryKey="false"
			required="true"
			autoinc="false"
			logicDeleteMark="false">
			<fk_info entity="cause.xml"
						referencedField="id"
						substituteField="description">
			</fk_info>	</field>
</entity>